LICENSE
MANIFEST.in
README.md
requirements.txt
setup.py
pyauto/__init__.py
pyauto.util.egg-info/PKG-INFO
pyauto.util.egg-info/SOURCES.txt
pyauto.util.egg-info/dependency_links.txt
pyauto.util.egg-info/requires.txt
pyauto.util.egg-info/top_level.txt
pyauto/util/__init__.py
pyauto/util/diffutil.py
pyauto/util/digitalocean.py
pyauto/util/funcutil.py
pyauto/util/gzutil.py
pyauto/util/j2util.py
pyauto/util/strutil.py
pyauto/util/uriutil.py
pyauto/util/yamlutil.py
pyauto/util/ziputil.py