Metadata-Version: 1.0
Name: pyauto.util
Version: 0.2.1
Summary: Utility functions
Home-page: https://github.com/adamjaso/pyauto
Author: Adam Jaso
Author-email: UNKNOWN
License: GNU General Public License V2
Platform: UNKNOWN
